setup.py
mbed_test_wrapper/__init__.py
mbed_test_wrapper/main.py
mbed_test_wrapper.egg-info/PKG-INFO
mbed_test_wrapper.egg-info/SOURCES.txt
mbed_test_wrapper.egg-info/dependency_links.txt
mbed_test_wrapper.egg-info/entry_points.txt
mbed_test_wrapper.egg-info/top_level.txt