Metadata-Version: 1.1
Name: mbed-test-wrapper
Version: 0.0.3
Summary: Wrap the mbed test loader for easy use from yotta targets.
Home-page: about:blank
Author: James Crosby
Author-email: James.Crosby@arm.com
License: Apache-2.0
Keywords: mbed test script
Platform: UNKNOWN
Classifier: Development Status :: 3 - Alpha
Classifier: Topic :: Utilities
Classifier: License :: OSI Approved :: Apache Software License
Classifier: Environment :: Console
